{
  "updated_at": 1758225836,
  "products": [
    {
      "source": "ebay",
      "keyword": "portable monitor",
      "title": "Lifelong Portable Monitor 15.6\" 1080P Model G70",
      "price": 29.99,
      "currency": "USD",
      "image_url": "https://i.ebayimg.com/images/g/aUYAAOSwl3pneDH~/s-l225.jpg",
      "url": "https://www.ebay.com/itm/277164929009?_skw=portable+monitor&hash=item4088512ff1%3Ag%3AaUYAAOSwl3pneDH~&mkcid=1&mkrid=711-53200-19255-0&mkevt=1&campid=5339121799&customid=portable_monitor&toolid=10001",
      "seller_feedback": 20043,
      "top_rated": false,
      "score": 9.0,
      "tags": [
        "portable monitor"
      ],
      "caption": "Elevate your productivity on-the-go with the Lifelong 15.6\" Portable Monitor! \ud83c\udf1f Grab yours now for just $29.99! \ud83d\udda5\ufe0f\u2728",
      "headline": "\ud83c\udf1f Grab Your Lifelong Portable Monitor for Just $29.99!",
      "blurb": "Limited stock available! Enhance your gaming and work experience on-the-go with this 15.6\" 1080P monitor. Order now and elevate your setup!",
      "emojis": "['\ud83d\udda5\ufe0f', '\ud83d\udd79\ufe0f']"
    },
    {
      "source": "ebay",
      "keyword": "portable monitor",
      "title": "Used 15.6\" Portable Monitor Upgraded IPS HDR 1080P Full HD Eye Care Screen USB C",
      "price": 49.99,
      "currency": "USD",
      "image_url": "https://i.ebayimg.com/images/g/ICIAAOSwnTtml5Di/s-l225.jpg",
      "url": "https://www.ebay.com/itm/314029464108?_skw=portable+monitor&hash=item491d9d5a2c%3Ag%3AICIAAOSwnTtml5Di&amdata=enc%3AAQAKAAAA8PeG5RIuIyokJHJy903%2F5UbU7LSUQ1MAg4PGpa7LhgDfa%2FEFb6ADbi8xrd1XPrBPBQ0IkNPU40iJLmjb3tVpuR6MbZUQ%2Bty6BNsQ9BsfMWNHCV3AK7wXTC8GVwCZxj1qbThYyWZQ2mUkDp3xHyS%2FkwqmFlLsKE7A319P9xwjkoGQXvjV%2F2pUV3jh9OJpgs%2BR3EGvJq1u5ZNV1e%2FEMzzsgf1%2BGidRaUB2AsR7Az9zN3j%2BzB9UZPGtlRUwjfahQJcZBLomkTZ0MlRuDYA8xIVUVGxgIDlEjGj2OA6YPnwT9bkFU%2FiRFNaeG0BEJ8BlXSjCRA%3D%3D&mkcid=1&mkrid=711-53200-19255-0&mkevt=1&campid=5339121799&customid=portable_monitor&toolid=10001",
      "seller_feedback": 4219,
      "top_rated": false,
      "score": 8.219000000000001,
      "tags": [
        "portable monitor"
      ],
      "caption": "Transform your workspace with our 15.6\" Portable Monitor! \ud83c\udf89 Experience stunning 1080P clarity. Grab yours now for just $49.99! \ud83d\udda5\ufe0f\u2728",
      "headline": "\ud83d\udda5\ufe0f Upgrade Your Setup with This Portable Monitor!",
      "blurb": "Don't miss out on this limited-time offer! Get the Used 15.6\" IPS HDR monitor for just $49.99 and enhance your viewing experience. Order now!",
      "emojis": "['\ud83d\udda5\ufe0f', '\ud83d\udd0c', '\u2728']"
    },
    {
      "source": "ebay",
      "keyword": "portable monitor",
      "title": "UPERFECT 22 Inch Portable Monitor 2K 2560*1440 Laptop Display Computer Monitor",
      "price": 149.99,
      "currency": "USD",
      "image_url": "https://i.ebayimg.com/images/g/JpEAAOSwTgdmx41H/s-l225.jpg",
      "url": "https://www.ebay.com/itm/315692006992?_skw=portable+monitor&hash=item4980b5be50%3Ag%3AJpEAAOSwTgdmx41H&amdata=enc%3AAQAKAAAA8PeG5RIuIyokJHJy903%2F5UYE29t2LgkTgZ46o8dehQSE4BqA8WkuhOYUU%2BwR%2BUFIWWwAu%2BCWsHHd%2FNS%2FYBJOI7L603T7FiX97m5w8r6kbA4b3QIpecg52Ue0HIWPZ3mrwvt%2FguQy%2B9sPGd2NzPWNTEX3IJx9rt3RRfA51S%2F7%2Bn6k9Wb%2FDqF0G%2BZ9i2XVKauCGJCZoz2eIdbHPQnguIYDAmM22IXiy2OQrCuVvNtwULqnJTwLjsbupIvASBXgFQ1fx03O4Xv9hnI%2BfZLRfjyLNwTJjURZL8lDzGGm3ZDXTl3CnuYkyOZPr%2BlWuBa3u2VwNA%3D%3D&mkcid=1&mkrid=711-53200-19255-0&mkevt=1&campid=5339121799&customid=portable_monitor&toolid=10001",
      "seller_feedback": 4219,
      "top_rated": false,
      "score": 8.219000000000001,
      "tags": [
        "portable monitor"
      ],
      "caption": "Transform your workspace with the UPERFECT 22\" 2K Portable Monitor! \ud83d\ude80 Grab yours now for only $149.99 and elevate your setup!",
      "headline": "Upgrade Your Setup! \ud83d\ude80 22\" Portable 2K Monitor",
      "blurb": "Transform your workspace with the UPERFECT 22\" Portable Monitor at just $149.99! Limited stock available\u2014grab yours now and enjoy stunning visuals on the go! \ud83d\udda5\ufe0f\u2728",
      "emojis": "['\ud83d\ude80', '\ud83d\udda5\ufe0f', '\u2728']"
    },
    {
      "source": "ebay",
      "keyword": "portable monitor",
      "title": "UPERFECT 16\" 2K 120Hz Portable Monitor 2*USB C Extend Display For Game Switch PS",
      "price": 95.99,
      "currency": "USD",
      "image_url": "https://i.ebayimg.com/images/g/7yAAAOSw~kZmJdaI/s-l225.jpg",
      "url": "https://www.ebay.com/itm/313472386520?_skw=portable+monitor&hash=item48fc6905d8%3Ag%3A7yAAAOSw~kZmJdaI&amdata=enc%3AAQAKAAAA8PeG5RIuIyokJHJy903%2F5UbKXuoSEGV3S8t1CiTUvRGRCjvP41Oz2jk87bLxWJfh1Vv6G6gEozoXaESgwvfWi80aKNXvx0%2BZrnGxJxhPO%2BSFy8%2FMVVluuOVWH0r0A%2B5nuaJQVYzaKXZVyEEgQ7JS7TvAiIDDaBBzDP0%2Fco5ut%2BJH2dulDlyyGadCDGrfF%2BQZkN1X3knNo1Fz8S7PqeVsM50n0o7crQbaHPWIxDqcWOoZTvar71q6ho5fb0dl9BT6bBsgcZWzwsSgYPPdY3MCfJYf%2B9UdRBOtvdu0sB%2BPItjNLujwbF9eM8fkoKoH1bEwsg%3D%3D&mkcid=1&mkrid=711-53200-19255-0&mkevt=1&campid=5339121799&customid=portable_monitor&toolid=10001",
      "seller_feedback": 4219,
      "top_rated": false,
      "score": 8.219000000000001,
      "tags": [
        "portable monitor"
      ],
      "caption": "Elevate your gaming with the UPERFECT 16\" 2K 120Hz Portable Monitor! \ud83d\udd79\ufe0f Grab yours now for just $95.99 and level up your play!",
      "headline": "\ud83c\udf1f Elevate Your Gaming Anywhere with UPERFECT Monitor!",
      "blurb": "Don't miss out on this limited-time offer! Grab the UPERFECT 16\" 2K Portable Monitor for just $95.99 and enhance your gaming experience on-the-go. Order now!",
      "emojis": "['\ud83d\udd79\ufe0f', '\ud83c\udfae']"
    },
    {
      "source": "ebay",
      "keyword": "portable monitor",
      "title": "UPERFECT 24\" USB-C Portable Monitor 1920x1080 120Hz Display For Raspberry PI PS",
      "price": 118.99,
      "currency": "USD",
      "image_url": "https://i.ebayimg.com/images/g/CWoAAeSwNlFofz3G/s-l225.jpg",
      "url": "https://www.ebay.com/itm/392992502359?_skw=portable+monitor&hash=item5b802db257%3Ag%3ACWoAAeSwNlFofz3G&amdata=enc%3AAQAKAAAA8PeG5RIuIyokJHJy903%2F5UaCAvkCF9YX0iz7%2BD3PYhhewLjesf9u%2BvLEDm1kCf5KeIAOLax9v7%2FZ5T4yPh1cfkH4pATR2bh5FTc06X4emkQRG8FW%2BrhTfT05GSu%2FUW5gcZgQk%2FLHJBPOZh%2BHc5T257%2Fbcx%2Ff2aJzmzVnuvArqusWp%2BNrbeKMT33Z8Yzl4PANMJxZ0YlFGozh9489ROvbzIQ7jWqACLm8lX3qN8wnbVcenfyUqzzfH6ZEzaP4QgyuwExiCLgBSeoEb%2FQ2txcCYBxmE1lWAwGT4OwmElBo3NEB4AmaHUJsIPjg5hOHbfYf6g%3D%3D&mkcid=1&mkrid=711-53200-19255-0&mkevt=1&campid=5339121799&customid=portable_monitor&toolid=10001",
      "seller_feedback": 3859,
      "top_rated": false,
      "score": 7.859,
      "tags": [
        "portable monitor"
      ],
      "caption": "Elevate your gaming and productivity with the UPERFECT 24\" USB-C Monitor! \ud83c\udfae Grab yours now for just $118.99 and level up your setup! \ud83d\ude80",
      "headline": "\ud83d\udd25 Upgrade Your Setup with the UPERFECT 24\" Portable Monitor!",
      "blurb": "Boost your productivity on the go with a stunning 120Hz display. Limited stock available\u2014grab yours now!",
      "emojis": "['\ud83d\udda5\ufe0f', '\u26a1']"
    }
  ]
}