{
  "updated_at": 1764176675,
  "products": [
    {
      "source": "ebay",
      "provider": "ebay",
      "keyword": "smart light strip",
      "title": "Smart Permanent Outdoor Lights RGB Waterproof Eaves Lighting for House Decor",
      "price": 29.99,
      "currency": "USD",
      "image_url": "https://i.ebayimg.com/images/g/V5QAAeSwumhpEk3Z/s-l225.jpg",
      "url": "https://www.ebay.com/itm/306594801151?_skw=smart+light+strip&hash=item47627965ff%3Ag%3AV5QAAeSwumhpEk3Z&amdata=enc%3AAQAKAAAA8PeG5RIuIyokJHJy903%2F5UYGlpVXEsPUUtirhxueh1EDkJ4ueDCaRIceyLcrKBS5Tlqt0VIVDV8nNOkiZgGaSppzwduSgIRZhK%2FMkiGt5mJ1l3OJrJvsW3Rl8jlou4IFbZL6Lb6QYwS5JGMyprInqMbxvy%2FD6C8MSEhz%2B3aT%2FjKhReZW6aCV6zd5GhEOwXbFQQRch8hvwA0Sv%2B0R7Xe4NTK2lAVM9WixyBsPly4S%2Feg10JgjG2BtufzY5%2FAYJ%2FXuUEh3nl84t5eKO2Shz%2BW82G5CMsIeXMxyZx47clJXwjp9b2yWSRf5Qbq%2F7FfbybddIg%3D%3D&mkcid=1&mkrid=711-53200-19255-0&mkevt=1&campid=5339121799&customid=smart_light_strip&toolid=10001",
      "seller_feedback": 6686,
      "top_rated": false,
      "score": 9.0,
      "tags": [
        "smart light strip"
      ],
      "caption": "Transform your home with our Smart RGB Outdoor Lights! \ud83c\udf08 Elevate your decor for just $29.99. Grab yours now! \u2728",
      "headline": "\ud83d\udd25\u2728 Smart Permanent Outdoor Lights RGB Waterproof Eaves Lighting for House Decor",
      "blurb": "USD 29.99 steal. Limited stock\u2014grab it now!",
      "emojis": "\ud83d\udd25\u2728"
    },
    {
      "source": "ebay",
      "provider": "ebay",
      "keyword": "smart light strip",
      "title": "100Ft LED Strip Lights, Smart Light with App Remote Control, RGB LED Lights for ",
      "price": 14.89,
      "currency": "USD",
      "image_url": "https://i.ebayimg.com/images/g/KuUAAOSwoXdmKC4-/s-l225.jpg",
      "url": "https://www.ebay.com/itm/266782459674?_skw=smart+light+strip&hash=item3e1d79471a%3Ag%3AKuUAAOSwoXdmKC4-&amdata=enc%3AAQAKAAAA8PeG5RIuIyokJHJy903%2F5UZqOE8xMOfSf8n1qsjMl85rqejuJFexeKdJ66PrQdGaBUO35B73Teu7uQIT%2FbN1wVlR75i0aPOL6WUnApR3layvXYs1mIxffVkpzoGn5lwxKd2ekNxZWiZiUzpGMy56oxezx%2FlUb6kn5YJ8viVltLDiIQBvz2BGyabACKuuubxL49CVs2jUwuwldwzYWnv4CvU0cWfGemQ6oXKymRb0lmQfohgN5HZTLvoLuahgzd6svdeP9HvVnZbAEZJmJE5%2BXfnkq8SayKOT2m7un5E067DXJNrMQ%2FvbjQ%2BiZ1iExK2wUg%3D%3D&mkcid=1&mkrid=711-53200-19255-0&mkevt=1&campid=5339121799&customid=smart_light_strip&toolid=10001",
      "seller_feedback": 9031,
      "top_rated": false,
      "score": 7.0,
      "tags": [
        "smart light strip"
      ],
      "caption": "100Ft LED Strip Lights, Smart Light with App Remote Control, RGB LED Lights for  \u2022 USD 14.89",
      "headline": "\ud83d\udd25\u2728 100Ft LED Strip Lights, Smart Light with App Remote Control, RGB LED Lights for",
      "blurb": "USD 14.89 steal. Limited stock\u2014grab it now!",
      "emojis": "\ud83d\udd25\u2728"
    },
    {
      "source": "ebay",
      "provider": "ebay",
      "keyword": "smart light strip",
      "title": "eufy Permanent Outdoor Light E22 100ft Smart Light Strip App Control IP67|Refurb",
      "price": 174.99,
      "currency": "USD",
      "image_url": "https://i.ebayimg.com/images/g/5Y8AAOSw6oBnrBYm/s-l225.jpg",
      "url": "https://www.ebay.com/itm/384708438760?_skw=smart+light+strip&hash=item599268eae8%3Ag%3A5Y8AAOSw6oBnrBYm&amdata=enc%3AAQAKAAAA8PeG5RIuIyokJHJy903%2F5UY8yA9rW4Ql%2BJ7xrC%2BJ0biHokSpkevaKXP4LYB9SHYUGVDWXWVh4xYOftqCLIfJ899EUREVpXwDPqPyKzpGOK38oYPByyvtXKjSRZpoBK6HAzx%2BHfkLNIcgFbxef3lV8HL2tCPdTg82cOwgRJOoPsRDuF8bZBNKSH3g1RlUHlT1fWcmQkJRNZ89Os9FQTXeKRKctWLr11rXf1BJM4pPvB87aEAsK81UPILWRWsmFx%2B1JucFXjPANcBqQpsVQ%2ByLsjEbS5OSuN0OKzAB633RHtTXLvnpbggopCAaxdzGt0TajQ%3D%3D&mkcid=1&mkrid=711-53200-19255-0&mkevt=1&campid=5339121799&customid=smart_light_strip&toolid=10001",
      "seller_feedback": 68907,
      "top_rated": false,
      "score": 6.0,
      "tags": [
        "smart light strip"
      ],
      "caption": "eufy Permanent Outdoor Light E22 100ft Smart Light Strip App Control IP67|Refurb \u2022 USD 174.99",
      "headline": "\ud83d\udd25\u2728 eufy Permanent Outdoor Light E22 100ft Smart Light Strip App Control IP67|Refurb",
      "blurb": "USD 174.99 steal. Limited stock\u2014grab it now!",
      "emojis": "\ud83d\udd25\u2728"
    },
    {
      "source": "ebay",
      "provider": "ebay",
      "keyword": "smart light strip",
      "title": "200 Ft LED Strip Lights, Smart Light with App Remote Control, RGB LED 2ROLL100ft",
      "price": 20.89,
      "currency": "USD",
      "image_url": "https://i.ebayimg.com/images/g/~FsAAOSw~W5oXN1B/s-l225.jpg",
      "url": "https://www.ebay.com/itm/376365776719?_skw=smart+light+strip&hash=item57a125ff4f%3Ag%3A~FsAAOSw~W5oXN1B&amdata=enc%3AAQAKAAAA8PeG5RIuIyokJHJy903%2F5UYIIlNE9M2vb37thPq24N9FYmLKHIN%2B%2FP9LFrCWcqvNkrijB66RSqZaHz%2B%2BqLx%2Fo0F8L9c%2BfIjP%2Fem4lnYUot3zO9Ww3hHoad41qGjbo29TZdCH29vBhYjrYGgCr1EQQPhhY7XSG%2BQtVzcq37iQnqhA%2BsGqkRYim2MVM%2B1Rp%2BRvzt%2BKBgnGJmC7i2J7VUANN76u%2BuZNc8F3bbracIt%2BdM2QgHlJdA3XzIyodo9GHzXz9MM1vTESkrYG11RtyBmdF27NF0kZBXokIHARsbA7SFc1s00tR7Kuv53iJjdbhk01zQ%3D%3D&mkcid=1&mkrid=711-53200-19255-0&mkevt=1&campid=5339121799&customid=smart_light_strip&toolid=10001",
      "seller_feedback": 277,
      "top_rated": false,
      "score": 4.277,
      "tags": [
        "smart light strip"
      ],
      "caption": "200 Ft LED Strip Lights, Smart Light with App Remote Control, RGB LED 2ROLL100ft \u2022 USD 20.89",
      "headline": "\ud83d\udd25\u2728 200 Ft LED Strip Lights, Smart Light with App Remote Control, RGB LED 2ROLL100ft",
      "blurb": "USD 20.89 steal. Limited stock\u2014grab it now!",
      "emojis": "\ud83d\udd25\u2728"
    },
    {
      "source": "ebay",
      "provider": "ebay",
      "keyword": "smart light strip",
      "title": "LED Strip Lights, Smart Light with App Remote Control, RGB LED Lights for room",
      "price": 12.34,
      "currency": "USD",
      "image_url": "https://i.ebayimg.com/images/g/9G4AAOSwkx1oHAv2/s-l225.jpg",
      "url": "https://www.ebay.com/itm/376279396326?_skw=smart+light+strip&var=644967368880&hash=item579bffefe6%3Ag%3A9G4AAOSwkx1oHAv2&mkcid=1&mkrid=711-53200-19255-0&mkevt=1&campid=5339121799&customid=smart_light_strip&toolid=10001",
      "seller_feedback": 277,
      "top_rated": false,
      "score": 2.277,
      "tags": [
        "smart light strip"
      ],
      "caption": "LED Strip Lights, Smart Light with App Remote Control, RGB LED Lights for room \u2022 USD 12.34",
      "headline": "\ud83d\udd25\u2728 LED Strip Lights, Smart Light with App Remote Control, RGB LED Lights for room",
      "blurb": "USD 12.34 steal. Limited stock\u2014grab it now!",
      "emojis": "\ud83d\udd25\u2728"
    }
  ]
}