{
  "updated_at": 1764770763,
  "products": [
    {
      "source": "ebay",
      "provider": "ebay",
      "keyword": "portable monitor",
      "title": "Acer 16\" PM161Q ABMIUUZX Portable Widescreen LCD Monitor 1920\u00d71080 60Hz Refurb",
      "price": 40.49,
      "currency": "USD",
      "image_url": "https://i.ebayimg.com/images/g/G90AAeSwar5pG7CS/s-l225.jpg",
      "url": "https://www.ebay.com/itm/267228772305?_skw=portable+monitor&hash=item3e381377d1%3Ag%3AG90AAeSwar5pG7CS&mkcid=1&mkrid=711-53200-19255-0&mkevt=1&campid=5339121799&customid=portable_monitor&toolid=10001",
      "seller_feedback": 88996,
      "top_rated": false,
      "score": 9.0,
      "tags": [
        "portable monitor"
      ],
      "caption": "Acer 16\" PM161Q ABMIUUZX Portable Widescreen LCD Monitor 1920\u00d71080 60Hz Refurb \u2022 USD 40.49",
      "headline": "\ud83d\udd25\u2728 Acer 16\" PM161Q ABMIUUZX Portable Widescreen LCD Monitor 1920\u00d71080 60Hz Refurb",
      "blurb": "USD 40.49 steal. Limited stock\u2014grab it now!",
      "emojis": "\ud83d\udd25\u2728"
    },
    {
      "source": "ebay",
      "provider": "ebay",
      "keyword": "portable monitor",
      "title": "Used 15.6\" Portable Monitor Upgraded IPS HDR 1080P Full HD Eye Care Screen USB C",
      "price": 49.99,
      "currency": "USD",
      "image_url": "https://i.ebayimg.com/images/g/ICIAAOSwnTtml5Di/s-l225.jpg",
      "url": "https://www.ebay.com/itm/314029464108?_skw=portable+monitor&hash=item491d9d5a2c%3Ag%3AICIAAOSwnTtml5Di&amdata=enc%3AAQAKAAAA8PeG5RIuIyokJHJy903%2F5UbU7LSUQ1MAg4PGpa7LhgDfa%2FEFb6ADbi8xrd1XPrBPBQ0IkNPU40iJLmjb3tVpuR6MbZUQ%2Bty6BNsQ9BsfMWNHCV3AK7wXTC8GVwCZxj1qbThYyWZQ2mUkDp3xHyS%2Fkwow5rs08Mg2sb96Vt0rOGaIUSnjqT1AZdquk%2FwydofMv3mj%2B4Lk9kqlCGuE0ArKyegoQQjt9qU9FeSXmjAwAqsTO0ESDqMIFKlHBKmboCv8F5DH%2BpIzltbAQaH0uJDWZwErtHCqoDrPV%2FneDKYNAP3DYdemUZiXkEoYy4L4KtjDeA%3D%3D&mkcid=1&mkrid=711-53200-19255-0&mkevt=1&campid=5339121799&customid=portable_monitor&toolid=10001",
      "seller_feedback": 4358,
      "top_rated": false,
      "score": 8.358,
      "tags": [
        "portable monitor"
      ],
      "caption": "Used 15.6\" Portable Monitor Upgraded IPS HDR 1080P Full HD Eye Care Screen USB C \u2022 USD 49.99",
      "headline": "\ud83d\udd25\u2728 Used 15.6\" Portable Monitor Upgraded IPS HDR 1080P Full HD Eye Care Screen USB C",
      "blurb": "USD 49.99 steal. Limited stock\u2014grab it now!",
      "emojis": "\ud83d\udd25\u2728"
    },
    {
      "source": "ebay",
      "provider": "ebay",
      "keyword": "portable monitor",
      "title": "UPERFECT 16\" 2K 120Hz Portable Monitor 2*USB C Extend Display For Game Switch PS",
      "price": 99.99,
      "currency": "USD",
      "image_url": "https://i.ebayimg.com/images/g/7yAAAOSw~kZmJdaI/s-l225.jpg",
      "url": "https://www.ebay.com/itm/313472386520?_skw=portable+monitor&hash=item48fc6905d8%3Ag%3A7yAAAOSw~kZmJdaI&amdata=enc%3AAQAKAAAA8PeG5RIuIyokJHJy903%2F5UbKXuoSEGV3S8t1CiTUvRGRCjvP41Oz2jk87bLxWJfh1Vv6G6gEozoXaESgwvfWi80aKNXvx0%2BZrnGxJxhPO%2BSFy8%2FMVVluuOVWH0r0A%2B5nuaJQVYzaKXZVyEEgQ7JS7Ttwz0NdAKKhu1MC49gSnnYGtcq46fylmD9jWFY8eEiehho8Jpaf1m%2BIW3Ii7mbFLBhn%2Fh6w%2ByAhsCLZlC4%2Fbac%2F9wR2KuZcQOiUK5HuEN4w3LBw%2FYlEKeqIxIQO%2FK%2FK3MMvKhoqygKNBIeNUrHlOJmVd92rMkxqoyjHxbSSSdAU4w%3D%3D&mkcid=1&mkrid=711-53200-19255-0&mkevt=1&campid=5339121799&customid=portable_monitor&toolid=10001",
      "seller_feedback": 4358,
      "top_rated": false,
      "score": 8.358,
      "tags": [
        "portable monitor"
      ],
      "caption": "UPERFECT 16\" 2K 120Hz Portable Monitor 2*USB C Extend Display For Game Switch PS \u2022 USD 99.99",
      "headline": "\ud83d\udd79\ufe0f UPERFECT 16\" 2K 120Hz Portable Monitor 2*USB C Extend Display For Game Switch PS",
      "blurb": "USD 99.99 steal. Limited stock\u2014grab it now!",
      "emojis": "\ud83d\udd79\ufe0f\ud83c\udfae\u2728"
    },
    {
      "source": "ebay",
      "provider": "ebay",
      "keyword": "portable monitor",
      "title": "UPERFECT 22 Inch Portable Monitor 2K 2560*1440 Laptop Display Computer Monitor",
      "price": 134.26,
      "currency": "USD",
      "image_url": "https://i.ebayimg.com/images/g/JpEAAOSwTgdmx41H/s-l225.jpg",
      "url": "https://www.ebay.com/itm/315692006992?_skw=portable+monitor&hash=item4980b5be50%3Ag%3AJpEAAOSwTgdmx41H&amdata=enc%3AAQAKAAAA8PeG5RIuIyokJHJy903%2F5UYE29t2LgkTgZ46o8dehQSE4BqA8WkuhOYUU%2BwR%2BUFIWWwAu%2BCWsHHd%2FNS%2FYBJOI7L603T7FiX97m5w8r6kbA4b3QIpecg52Ue0HIWPZ3mrwvt%2FguQy%2B9sPGd2NzPWNTEVoZR8%2BYo5LyX7TuSxWdmZsME1OOlHCKvw8VChTSz4aCStDPUqWRCsqpGUJvPg8WzmEu2COhXWLxGwfLAENVkIL0wejD9O8mupGKDzuvpKDJHAo1utSDvrSwG6DmSlZ4MB1Dmho4IaNw6LkyQBmLShlaPsqBkmEzHPr9TOCtA9%2Fqw%3D%3D&mkcid=1&mkrid=711-53200-19255-0&mkevt=1&campid=5339121799&customid=portable_monitor&toolid=10001",
      "seller_feedback": 4358,
      "top_rated": false,
      "score": 8.358,
      "tags": [
        "portable monitor"
      ],
      "caption": "Transform your workspace with the UPERFECT 22\" Portable Monitor! \ud83c\udf1f Elevate your productivity today\u2014grab yours now!",
      "headline": "\ud83d\udd25\u2728 UPERFECT 22 Inch Portable Monitor 2K 2560*1440 Laptop Display Computer Monitor",
      "blurb": "USD 134.26 steal. Limited stock\u2014grab it now!",
      "emojis": "\ud83d\udd25\u2728"
    },
    {
      "source": "ebay",
      "provider": "ebay",
      "keyword": "portable monitor",
      "title": "Used | 16\u201d 120Hz Monitor 2K Portable Monitor USB C Gaming Monitor Freesync",
      "price": 62.99,
      "currency": "USD",
      "image_url": "https://i.ebayimg.com/images/g/GIUAAOSwECFlCtge/s-l225.jpg",
      "url": "https://www.ebay.com/itm/225980562840?_skw=portable+monitor&hash=item349d7dbd98%3Ag%3AGIUAAOSwECFlCtge&amdata=enc%3AAQAKAAAA8PeG5RIuIyokJHJy903%2F5UaNv6suWFWynZ6VQnjCZUKc0bz88o0CHo6MgfP%2BAhK3PLliKT9czkG7LCXXg%2BvUDgoZFm6aR3XJaGa0IYNjQA4uybqHoE7anu5AN8wG8GV9016tmvPUXsJ7bpJfR1tr01%2FMYaCdmGgC%2Bj9ZqzRhIqcsn9lW1t5iSSqOLkgW3Tn8hWz8Dl%2F7ZXgqblgIMrnSopw7fPMFU%2FVcVeKT%2BMqAOxmVH3JfvNSUJw9llnU11gOSiqsSPAMXdGAFvMtp8sfeENG2O6Gn6z7hWcYxrJeqNy5iK36UXbKNtJWZssC70XBb%2Fg%3D%3D&mkcid=1&mkrid=711-53200-19255-0&mkevt=1&campid=5339121799&customid=portable_monitor&toolid=10001",
      "seller_feedback": 3717,
      "top_rated": false,
      "score": 7.7170000000000005,
      "tags": [
        "portable monitor"
      ],
      "caption": "Used | 16\u201d 120Hz Monitor 2K Portable Monitor USB C Gaming Monitor Freesync \u2022 USD 62.99",
      "headline": "\ud83d\udd79\ufe0f Used | 16\u201d 120Hz Monitor 2K Portable Monitor USB C Gaming Monitor Freesync",
      "blurb": "USD 62.99 steal. Limited stock\u2014grab it now!",
      "emojis": "\ud83d\udd79\ufe0f\ud83c\udfae\u2728"
    }
  ]
}