{
  "updated_at": 1763849045,
  "products": [
    {
      "source": "ebay",
      "provider": "ebay",
      "keyword": "rgb lamp",
      "title": "Govee Aura Smart RGBIC Table Lamp App Control Bedside Rainbow Lamp USED",
      "price": 24.99,
      "currency": "USD",
      "image_url": "https://i.ebayimg.com/images/g/dicAAOSwI89mg04b/s-l225.jpg",
      "url": "https://www.ebay.com/itm/366002318190?_skw=rgb+lamp&hash=item5537702b6e%3Ag%3AdicAAOSwI89mg04b&amdata=enc%3AAQAKAAAA4PeG5RIuIyokJHJy903%2F5UZGfNc7NPk%2BbORU4lAp1ood7VH0TMLsn7Xkpgge4Ni7z3OK9Dd3lUAjof%2FgrqVvGKNHorVqsqTJBCssDr8GT5UAldPTUdDvLkE9SnT6aeAlJCCQXf2EQW5wXoUxiXLL88jqECa%2BpuiXWWX2mNuuQ1qT8hikqja1h6Es3juyf5DwuBwZUORHBP9Ng4sd1iv%2B5lPEH%2FLmWMqzMM606nWSbnlRIMFciVP6SBHzrqutkhYBjFKcVm0ruYnTKxgM6BO7nIJ%2BRlZdVC9LnzDw8vHnd5KD&mkcid=1&mkrid=711-53200-19255-0&mkevt=1&campid=5339121799&customid=rgb_lamp&toolid=10001",
      "seller_feedback": 44038,
      "top_rated": false,
      "score": 9.0,
      "tags": [
        "rgb lamp"
      ],
      "caption": "Govee Aura Smart RGBIC Table Lamp App Control Bedside Rainbow Lamp USED \u2022 USD 24.99",
      "headline": "\ud83c\udfe0\ud83d\udecb Govee Aura Smart RGBIC Table Lamp App Control Bedside Rainbow Lamp USED",
      "blurb": "USD 24.99 steal. Limited stock\u2014grab it now!",
      "emojis": "\ud83c\udfe0\ud83d\udecb\ufe0f\u2728"
    },
    {
      "source": "ebay",
      "provider": "ebay",
      "keyword": "rgb lamp",
      "title": "Corner Floor Lamp 60\u201d Color Changing LED Floor Lamp with Music Sync Modern Mood",
      "price": 21.88,
      "currency": "USD",
      "image_url": "https://i.ebayimg.com/images/g/FwMAAOSwJX1oSob~/s-l225.jpg",
      "url": "https://www.ebay.com/itm/388947445591?_skw=rgb+lamp&hash=item5a8f130757%3Ag%3AFwMAAOSwJX1oSob~&amdata=enc%3AAQAKAAAA4PeG5RIuIyokJHJy903%2F5UayvWR%2F1JOsk7q5ajJNc%2BFluhOEp1Mp47vgw6wS0Lx7sZqGqVNkWBlcxaaJ%2BmDwspJu55pcYHkEQKyIlrmxMLwFkkAvPB48K3KdrYAVPWTEmsLcPN0aeu%2BuRctjuER6uKn5SfqfrH2fU3LonbIwqQC6Ha1xS3aCm0PI3mQWzAgYWpgDLw6xBvfUUIt6aiLuya0VXGoknp4Sb43UBTIXGsVvnHGifRAQzoeDmQKmzqdA1ejWrqYvl3Kc02gHiNw5lF7C9y6P7W2IukifXh3dVacG&mkcid=1&mkrid=711-53200-19255-0&mkevt=1&campid=5339121799&customid=rgb_lamp&toolid=10001",
      "seller_feedback": 13547,
      "top_rated": false,
      "score": 9.0,
      "tags": [
        "rgb lamp"
      ],
      "caption": "Corner Floor Lamp 60\u201d Color Changing LED Floor Lamp with Music Sync Modern Mood \u2022 USD 21.88",
      "headline": "\ud83c\udfe0\ud83d\udecb Corner Floor Lamp 60\u201d Color Changing LED Floor Lamp with Music Sync Modern Mood",
      "blurb": "USD 21.88 steal. Limited stock\u2014grab it now!",
      "emojis": "\ud83c\udfe0\ud83d\udecb\ufe0f\u2728"
    },
    {
      "source": "ebay",
      "provider": "ebay",
      "keyword": "rgb lamp",
      "title": "2Pack RGB LED Corner Floor Lamp Minimalist Mood Light Colour Changing w/Remote",
      "price": 20.99,
      "currency": "USD",
      "image_url": "https://i.ebayimg.com/images/g/I3sAAeSwDaVo6hOB/s-l225.jpg",
      "url": "https://www.ebay.com/itm/136575707238?_skw=rgb+lamp&hash=item1fcc8be866%3Ag%3AI3sAAeSwDaVo6hOB&mkcid=1&mkrid=711-53200-19255-0&mkevt=1&campid=5339121799&customid=rgb_lamp&toolid=10001",
      "seller_feedback": 18771,
      "top_rated": false,
      "score": 9.0,
      "tags": [
        "rgb lamp"
      ],
      "caption": "2Pack RGB LED Corner Floor Lamp Minimalist Mood Light Colour Changing w/Remote \u2022 USD 20.99",
      "headline": "\ud83c\udfe0\ud83d\udecb 2Pack RGB LED Corner Floor Lamp Minimalist Mood Light Colour Changing w/Remote",
      "blurb": "USD 20.99 steal. Limited stock\u2014grab it now!",
      "emojis": "\ud83c\udfe0\ud83d\udecb\ufe0f\u2728"
    },
    {
      "source": "ebay",
      "provider": "ebay",
      "keyword": "rgb lamp",
      "title": "2-Pack Corner Floor Lamp,Lamps for Living Room with Smart App and Remote Control",
      "price": 39.99,
      "currency": "USD",
      "image_url": "https://i.ebayimg.com/images/g/euYAAeSwoPhn-Gil/s-l225.jpg",
      "url": "https://www.ebay.com/itm/335905894169?_skw=rgb+lamp&hash=item4e358d2f19%3Ag%3AeuYAAeSwoPhn-Gil&amdata=enc%3AAQAKAAAA4PeG5RIuIyokJHJy903%2F5UbYYpeoQbLdsV58qmls5lsc7iJQZ7HijZvXB9YYwremiTZh4CKV4SrTL%2Fs1Lb50ipMg2dybQlQf3ynaQB91zABzz3YknV3N9oZEsYX4RcB6A8mjyvE4nRM0mQqEPb09U%2BJqmLmcv6kTuetJKk2jK3DR%2FYKBJ0WHq3i%2FCsZI2azcP6vFqy4IlB4Hljmr1GdPcaS9swUHHRIV89nysC7U083FynPssvEXiXcmf9LpPgmKmU2CAENANwkgXx9wJWsXq6PE7McPJVPcZP5rsuc4pwes&mkcid=1&mkrid=711-53200-19255-0&mkevt=1&campid=5339121799&customid=rgb_lamp&toolid=10001",
      "seller_feedback": 3084,
      "top_rated": false,
      "score": 7.084,
      "tags": [
        "rgb lamp"
      ],
      "caption": "Brighten your space with our 2-Pack Corner Floor Lamps! \ud83c\udf1f Control them with your smartphone or remote. Grab yours now for just $39.99! \ud83d\uded2\u2728",
      "headline": "\ud83c\udfe0\ud83d\udecb 2-Pack Corner Floor Lamp,Lamps for Living Room with Smart App and Remote Control",
      "blurb": "USD 39.99 steal. Limited stock\u2014grab it now!",
      "emojis": "\ud83c\udfe0\ud83d\udecb\ufe0f\u2728"
    },
    {
      "source": "ebay",
      "provider": "ebay",
      "keyword": "rgb lamp",
      "title": "2\u00d7 47\" Smart LED Floor Lamp RGB Remote & APP Control Music Sync Corner Lighting",
      "price": 28.99,
      "currency": "USD",
      "image_url": "https://i.ebayimg.com/images/g/Vx0AAOSwHXBlZC4k/s-l225.jpg",
      "url": "https://www.ebay.com/itm/126722581126?_skw=rgb+lamp&hash=item1d81412286%3Ag%3AVx0AAOSwHXBlZC4k&amdata=enc%3AAQAKAAAA4PeG5RIuIyokJHJy903%2F5UaudNmsBl5NibrHAIuzTOoIxYZYeCZW%2FhY5xauxnjFhVovOoqRhYzbpPh%2FgZbSK7X6uWA4MulmDgdkunuoRgYp%2FhZfPpPejAb7UOo%2FfQfeWf4XBVVtHgh88u2M7QUQoMQRBxG3RIHZxqkm%2BrjGm3JAc9USSSAv%2Bj4vL0VwvNjvzlk4l6GEjlMuE8iwgUka1J%2Fl8jWlmzts69Kk1y195ZmB5DWRzxJCdurykZha3ZwoMnrzRPT%2Blilq2JzEp7t1Cgp6BKppesjTjLec1nLHxPaXM&mkcid=1&mkrid=711-53200-19255-0&mkevt=1&campid=5339121799&customid=rgb_lamp&toolid=10001",
      "seller_feedback": 2919,
      "top_rated": false,
      "score": 6.9190000000000005,
      "tags": [
        "rgb lamp"
      ],
      "caption": "2\u00d7 47\" Smart LED Floor Lamp RGB Remote & APP Control Music Sync Corner Lighting \u2022 USD 28.99",
      "headline": "\u2728 Transform Your Space with Smart RGB Floor Lamps!",
      "blurb": "Elevate your ambiance with our 2\u00d7 47\" Smart LED Floor Lamps for just $28.99! Hurry, limited stock available\u2014grab yours now!",
      "emojis": "['\ud83c\udfe0', '\ud83c\udfae']"
    }
  ]
}