{
  "updated_at": 1764277448,
  "products": [
    {
      "source": "ebay",
      "provider": "ebay",
      "keyword": "bike light",
      "title": "2 Set USB Rechargeable LED Bicycle Headlight Bike Front Rear Lamp Cycling Light",
      "price": 5.99,
      "currency": "USD",
      "image_url": "https://i.ebayimg.com/images/g/ZGYAAOSwTSdmob91/s-l225.jpg",
      "url": "https://www.ebay.com/itm/355897251030?_skw=bike+light&var=624956249515&hash=item52dd2114d6%3Ag%3AZGYAAOSwTSdmob91&amdata=enc%3AAQAKAAAA4PeG5RIuIyokJHJy903%2F5UaTkN02DYcV5TIPMI9q4C%2FN4Y9Q7sYMDQwEViFctow1roqYG1AScOswvyHbjYTM%2BNgvdBzhefWDKtH2uEWdpONwgx0vDHLzU7%2FrIDaFdn7hPJkEW09cSAdLhdUHlqXLseWsF6hpMEtSnDyQysc%2FumvfWbYk2cnskONT7V6VWjEhnQIzsZ4AGO6J1fqx0ygHvoDQNbWGCv%2FInQaPAT35wmKwWy5XRng%2FXfa4DG699XqJdO2A%2BmbJE%2B0M5M6vKYAfSir7M%2FAn4ZV9RGKO8%2BBju%2Bf8&mkcid=1&mkrid=711-53200-19255-0&mkevt=1&campid=5339121799&customid=bike_light&toolid=10001",
      "seller_feedback": 21910,
      "top_rated": false,
      "score": 7.0,
      "tags": [
        "bike light"
      ],
      "caption": "2 Set USB Rechargeable LED Bicycle Headlight Bike Front Rear Lamp Cycling Light \u2022 USD 5.99",
      "headline": "\ud83c\udfe0\ud83d\udecb 2 Set USB Rechargeable LED Bicycle Headlight Bike Front Rear Lamp Cycling Light",
      "blurb": "USD 5.99 steal. Limited stock\u2014grab it now!",
      "emojis": "\ud83c\udfe0\ud83d\udecb\ufe0f\u2728"
    },
    {
      "source": "ebay",
      "provider": "ebay",
      "keyword": "bike light",
      "title": "Waterproof Super Bright LED Bike Light USB Rechargeable Bicycle Front Headlight",
      "price": 14.95,
      "currency": "USD",
      "image_url": "https://i.ebayimg.com/images/g/hU4AAOSweJJky3kH/s-l225.jpg",
      "url": "https://www.ebay.com/itm/155700842635?_skw=bike+light&hash=item24407e508b%3Ag%3AhU4AAOSweJJky3kH&amdata=enc%3AAQAKAAAA4PeG5RIuIyokJHJy903%2F5UYZisDinTvuQEKSbfSePy6IUe4YnZaqX0jcfUXnRN3LYXl9UAPi4TDZa5wPbmOqeEoF9qow9O3zVGxgxE9%2F7cwNrdwy5JN1FoS4%2BA9I15QcjgmtXx%2BWaFxkmPdZo18G5L7avXValOkcptjHybfB07o67yLtIxiWkC46nnloYp1Gq0PvQ%2BZ%2FP%2B7RtRm4fMhiAXB93w9ujkzRtBbVxpCnyXC5Yhb%2FI435y6Pd7hUIALIbCRs%2Byk6KFNvXPCRaYxe4VnRN8kPcNfbrI99xKfjoNk1C&mkcid=1&mkrid=711-53200-19255-0&mkevt=1&campid=5339121799&customid=bike_light&toolid=10001",
      "seller_feedback": 235060,
      "top_rated": false,
      "score": 7.0,
      "tags": [
        "bike light"
      ],
      "caption": "Waterproof Super Bright LED Bike Light USB Rechargeable Bicycle Front Headlight \u2022 USD 14.95",
      "headline": "\ud83d\udd25\u2728 Waterproof Super Bright LED Bike Light USB Rechargeable Bicycle Front Headlight",
      "blurb": "USD 14.95 steal. Limited stock\u2014grab it now!",
      "emojis": "\ud83d\udd25\u2728"
    },
    {
      "source": "ebay",
      "provider": "ebay",
      "keyword": "bike light",
      "title": "2 Sets USB Rechargeable LED Bicycle Headlight Bike Front Rear Lamp Cycling Light",
      "price": 22.98,
      "currency": "USD",
      "image_url": "https://i.ebayimg.com/images/g/c7gAAOSw9ipmlJPy/s-l225.jpg",
      "url": "https://www.ebay.com/itm/126696923517?_skw=bike+light&hash=item1d7fb9a17d%3Ag%3Ac7gAAOSw9ipmlJPy&amdata=enc%3AAQAKAAAA4PeG5RIuIyokJHJy903%2F5UYYdeLkHPLNnokJ8gQxtkQmill%2BVAnQYhLbB4LAadKHnum0Oz6mlDsCp3rmtFqAsCE7MJbPFwIptMcTZO8B%2FvbPFIbowwmfwFM%2F0jfxYxT6paQsP7HOMLSC1naHLkLmB%2FEFd7TwPUDTXRP5f%2FLIUCn7AZxwiBh9T%2BbUDULCpRosew2XmRNeLwNc5isecXEJMUEvhKEocxaCJkQH%2BOlaHcOlIbthRegZuC8qYTB%2F1nntiSCgu7qOCQYhoQgLj1ON8i82mYufH0gf6sQYydccw9k9&mkcid=1&mkrid=711-53200-19255-0&mkevt=1&campid=5339121799&customid=bike_light&toolid=10001",
      "seller_feedback": 1502,
      "top_rated": false,
      "score": 5.502,
      "tags": [
        "bike light"
      ],
      "caption": "2 Sets USB Rechargeable LED Bicycle Headlight Bike Front Rear Lamp Cycling Light \u2022 USD 22.98",
      "headline": "\ud83c\udfe0\ud83d\udecb 2 Sets USB Rechargeable LED Bicycle Headlight Bike Front Rear Lamp Cycling Light",
      "blurb": "USD 22.98 steal. Limited stock\u2014grab it now!",
      "emojis": "\ud83c\udfe0\ud83d\udecb\ufe0f\u2728"
    },
    {
      "source": "ebay",
      "provider": "ebay",
      "keyword": "bike light",
      "title": "Waterproof LED Bike Light USB Rechargeable Super Bright Bicycle Front Headlight",
      "price": 14.99,
      "currency": "USD",
      "image_url": "https://i.ebayimg.com/images/g/9IcAAOSwjspnvsXq/s-l225.jpg",
      "url": "https://www.ebay.com/itm/405584915696?_skw=bike+light&hash=item5e6ebeacf0%3Ag%3A9IcAAOSwjspnvsXq&mkcid=1&mkrid=711-53200-19255-0&mkevt=1&campid=5339121799&customid=bike_light&toolid=10001",
      "seller_feedback": 1295,
      "top_rated": false,
      "score": 3.295,
      "tags": [
        "bike light"
      ],
      "caption": "Waterproof LED Bike Light USB Rechargeable Super Bright Bicycle Front Headlight \u2022 USD 14.99",
      "headline": "\ud83d\udd25\u2728 Waterproof LED Bike Light USB Rechargeable Super Bright Bicycle Front Headlight",
      "blurb": "USD 14.99 steal. Limited stock\u2014grab it now!",
      "emojis": "\ud83d\udd25\u2728"
    },
    {
      "source": "ebay",
      "provider": "ebay",
      "keyword": "bike light",
      "title": "NEW Bicycle Bike Wheel Lights 7 COLORS in 1 LED String Fits any Spoke Rim Tires",
      "price": 6.99,
      "currency": "USD",
      "image_url": "https://i.ebayimg.com/images/g/6tMAAOSwaiFi2tWT/s-l225.jpg",
      "url": "https://www.ebay.com/itm/175397899342?_skw=bike+light&hash=item28d6878c4e%3Ag%3A6tMAAOSwaiFi2tWT&amdata=enc%3AAQAKAAAA4PeG5RIuIyokJHJy903%2F5UYHBfyLfuRxjBUMHzI4FYQiR4XZ7LZVvAaJqx4iCcZVuvWd%2Be8HKyv0J3jxErs%2F3ja9LH3N0c6yC706brDqkocaLaOauV7pa0qZm8Ssch%2BwBCwl1qm4Xw48AMsGaohd7td%2F6Ol7N6F8ek1ldjlxwoDZW87xJhIAg7zbZnAkxT2TtzrOMejMgNjGS0iEAds%2F1jjy3dY1q9kqlet9EgSBiLn1%2FVggl9O1rteGXo%2B9ftYNxj13rqLxN%2F5vwXYtjqM0%2BrKsyOCuYepugitONUSC42TJ&mkcid=1&mkrid=711-53200-19255-0&mkevt=1&campid=5339121799&customid=bike_light&toolid=10001",
      "seller_feedback": 1274,
      "top_rated": false,
      "score": 3.274,
      "tags": [
        "bike light"
      ],
      "caption": "NEW Bicycle Bike Wheel Lights 7 COLORS in 1 LED String Fits any Spoke Rim Tires \u2022 USD 6.99",
      "headline": "\ud83d\udd25\u2728 Bicycle Bike Wheel Lights 7 COLORS in 1 LED String Fits any Spoke Rim Tires",
      "blurb": "USD 6.99 steal. Limited stock\u2014grab it now!",
      "emojis": "\ud83d\udd25\u2728"
    }
  ]
}