{
  "updated_at": 1760115857,
  "products": [
    {
      "source": "ebay",
      "keyword": "rgb lamp",
      "title": "Corner Floor Lamp 60\u201d Color Changing LED Floor Lamp with Music Sync Modern Mood",
      "price": 21.88,
      "currency": "USD",
      "image_url": "https://i.ebayimg.com/images/g/FwMAAOSwJX1oSob~/s-l225.jpg",
      "url": "https://www.ebay.com/itm/388947445591?_skw=rgb+lamp&hash=item5a8f130757%3Ag%3AFwMAAOSwJX1oSob~&amdata=enc%3AAQAKAAAA4PeG5RIuIyokJHJy903%2F5UayvWR%2F1JOsk7q5ajJNc%2BFlDIpGMtAC%2FEjCytdQzo0NJXvXoWl0VrjEWiOxYzVnmyknxfkoiy7wKQIqC99Dk5OXQJ4OGOSAy8rByg58z7TFPoB45Dl9refIZdTGIx%2BkzARvMszocPwZZILhDQzSE2CnPFy9kqIq3bx%2FngJmncdqyHbtX8WoN2jgU3tW9LvWdsqIAASYOC3IUk16do%2BEiK%2BooX99Xgak3v94hCs91LSz5zjD68%2BcbLS9qx7frAfztK%2FtzKaivXKKqbbxd3Ct%2FcOu&mkcid=1&mkrid=711-53200-19255-0&mkevt=1&campid=5339121799&customid=rgb_lamp&toolid=10001",
      "seller_feedback": 13143,
      "top_rated": false,
      "score": 9.0,
      "tags": [
        "rgb lamp"
      ],
      "caption": "Light up your space with our 60\u201d Color Changing LED Floor Lamp! \ud83c\udfb6 Sync with your music and set the mood! Grab yours now for just $21.88! \ud83d\uded2\u2728",
      "headline": "Illuminate Your Space! \ud83c\udf08",
      "blurb": "Transform your room with this stunning color-changing LED floor lamp! Limited stock at just $21.88\u2014grab yours now!",
      "emojis": "['\ud83c\udf08', '\ud83d\udca1']"
    },
    {
      "source": "ebay",
      "keyword": "rgb lamp",
      "title": "LED Floor Lamp, Corner Light Lamp RGB+ White Modern Smart Compatible with Alexa",
      "price": 27.99,
      "currency": "USD",
      "image_url": "https://i.ebayimg.com/images/g/CT8AAOSwXPpi~Q3b/s-l225.jpg",
      "url": "https://www.ebay.com/itm/275426095607?_skw=rgb+lamp&hash=item4020acb1f7%3Ag%3ACT8AAOSwXPpi~Q3b&amdata=enc%3AAQAKAAAA4PeG5RIuIyokJHJy903%2F5UYeB4073tMkbjMcdV%2FC0DDIrTMMo06%2Fmil5EshBvI8Lf8CBlZmtMl1weNLfV6MeTQxj%2FfKer7VW%2Bbd%2FHIx3Uwt4AZ%2FeicHX%2Br586KyphASYCAugVfAHDwdxfmfQdiFu6M84wYjvFnetVOYfncVykT70%2B9ZDOqud93J9F%2FQW8IGaolKF%2F5b%2Fzb3o1Lp6zX1gjBEYk6FbiO7BJS9Ipk9qD9AlWYAYaZWkSE7pXUq%2BfuDg%2B7D1zwpg%2B97n0R4tKuFks0qz%2Fw0ThLIEteB6DyfQ00Gi&mkcid=1&mkrid=711-53200-19255-0&mkevt=1&campid=5339121799&customid=rgb_lamp&toolid=10001",
      "seller_feedback": 9094,
      "top_rated": false,
      "score": 9.0,
      "tags": [
        "rgb lamp"
      ],
      "caption": "LED Floor Lamp, Corner Light Lamp RGB+ White Modern Smart Compatible with Alexa \u2022 USD 27.99",
      "headline": "\ud83c\udfe0\ud83d\udecb LED Floor Lamp, Corner Light Lamp RGB+ White Modern Smart Compatible with Alexa",
      "blurb": "USD 27.99 steal. Limited stock\u2014grab it now!",
      "emojis": "\ud83c\udfe0\ud83d\udecb\ufe0f\u2728"
    },
    {
      "source": "ebay",
      "keyword": "rgb lamp",
      "title": "12\" RGB Jellyfish Lamp with USB Black - West & Arrow: LED,",
      "price": 16.14,
      "currency": "USD",
      "image_url": "https://i.ebayimg.com/images/g/e6QAAeSwyTZo6NG~/s-l225.jpg",
      "url": "https://www.ebay.com/itm/205721100618?_skw=rgb+lamp&hash=item2fe5eee14a%3Ag%3Ae6QAAeSwyTZo6NG~&mkcid=1&mkrid=711-53200-19255-0&mkevt=1&campid=5339121799&customid=rgb_lamp&toolid=10001",
      "seller_feedback": 658135,
      "top_rated": false,
      "score": 9.0,
      "tags": [
        "rgb lamp"
      ],
      "caption": "Transform your space with the mesmerizing 12\" RGB Jellyfish Lamp! \ud83c\udf08 Grab yours now for just $16.14!\u2728",
      "headline": "\ud83c\udfe0\ud83d\udecb 12\" RGB Jellyfish Lamp with USB Black - West & Arrow: LED,",
      "blurb": "USD 16.14 steal. Limited stock\u2014grab it now!",
      "emojis": "\ud83c\udfe0\ud83d\udecb\ufe0f\u2728"
    },
    {
      "source": "ebay",
      "keyword": "rgb lamp",
      "title": "2\u00d7 47\" Smart LED Floor Lamp RGB Remote & APP Control Music Sync Corner Lighting",
      "price": 28.89,
      "currency": "USD",
      "image_url": "https://i.ebayimg.com/images/g/Vx0AAOSwHXBlZC4k/s-l225.jpg",
      "url": "https://www.ebay.com/itm/126722581126?_skw=rgb+lamp&hash=item1d81412286%3Ag%3AVx0AAOSwHXBlZC4k&amdata=enc%3AAQAKAAAA4PeG5RIuIyokJHJy903%2F5UaudNmsBl5NibrHAIuzTOoIxYZYeCZW%2FhY5xauxnjFhVovOoqRhYzbpPh%2FgZbSK7X6uWA4MulmDgdkunuoRgYp%2FhZfPpPejAb7UOo%2FfQfeWf4XBVVtHgh88u2M7QUQoMQTIyLNrsqjaHqk4iX9n9TfBweNZaiReIihHG7ygV5hutw3TEIjV2iuSbP7yNQdwA6wpnNyVL6U8Dtc1aTUR4Z9tCgR%2FdACkbGgzR4pL1wf4MYl%2Fgh8qd416hWNcl3qldy0C6QFewQsFZmWRHjy7vku0&mkcid=1&mkrid=711-53200-19255-0&mkevt=1&campid=5339121799&customid=rgb_lamp&toolid=10001",
      "seller_feedback": 2757,
      "top_rated": false,
      "score": 6.757,
      "tags": [
        "rgb lamp"
      ],
      "caption": "Transform your space with our 2\u00d7 47\" Smart LED Floor Lamps! \ud83c\udfb6 Control with ease & sync to your tunes. Grab yours now for just $28.89! \ud83d\uded2\u2728",
      "headline": "\ud83c\udfe0\ud83d\udecb 2\u00d7 47\" Smart LED Floor Lamp RGB Remote & APP Control Music Sync Corner Lighting",
      "blurb": "USD 28.89 steal. Limited stock\u2014grab it now!",
      "emojis": "\ud83c\udfe0\ud83d\udecb\ufe0f\u2728"
    },
    {
      "source": "ebay",
      "keyword": "rgb lamp",
      "title": "2 X Smart LED Floor Lamp RGB Remote & APP Control Music Sync Corner Lighting",
      "price": 29.98,
      "currency": "USD",
      "image_url": "https://i.ebayimg.com/images/g/JOsAAOSwatpnG2V0/s-l225.jpg",
      "url": "https://www.ebay.com/itm/126741630255?_skw=rgb+lamp&hash=item1d8263cd2f%3Ag%3AJOsAAOSwatpnG2V0&amdata=enc%3AAQAKAAAA4PeG5RIuIyokJHJy903%2F5UZIht%2BReaRxXAurUgWc4CtF%2BmWMhjYFuZmqORlFpp6ueZYheBMm6mgS5V04PGvV3k5NW5HM7KugPTZulDQUtEkz5FgDIO7ITy9i2OnAc52G8BqiK74VdbwKgqII%2BrUN4nSwyNzA22fxDbbsPrdG9UNK2cwbBvb4cNGAYisV%2BxLBJ1AQX%2FFBTj8Wp%2Fl0W41Kg%2BplWy8HSglG8%2B2KM2tvVRyZfZLskOIFZIqS52l0bq%2BSK8nOpv5wepMOQ3lcxoO0cruMObRkrDPexAoKautB6zfU&mkcid=1&mkrid=711-53200-19255-0&mkevt=1&campid=5339121799&customid=rgb_lamp&toolid=10001",
      "seller_feedback": 2757,
      "top_rated": false,
      "score": 6.757,
      "tags": [
        "rgb lamp"
      ],
      "caption": "2 X Smart LED Floor Lamp RGB Remote & APP Control Music Sync Corner Lighting \u2022 USD 29.98",
      "headline": "\ud83c\udfe0\ud83d\udecb 2 X Smart LED Floor Lamp RGB Remote & APP Control Music Sync Corner Lighting",
      "blurb": "USD 29.98 steal. Limited stock\u2014grab it now!",
      "emojis": "\ud83c\udfe0\ud83d\udecb\ufe0f\u2728"
    }
  ]
}