{
  "updated_at": 1763838258,
  "products": [
    {
      "source": "ebay",
      "provider": "ebay",
      "keyword": "smart light strip",
      "title": "Smart Permanent Outdoor Lights RGB Waterproof Eaves Lighting for House Decor",
      "price": 76.49,
      "currency": "USD",
      "image_url": "https://i.ebayimg.com/images/g/UOAAAeSwbgdpEgO6/s-l225.jpg",
      "url": "https://www.ebay.com/itm/116872006004?_skw=smart+light+strip&var=416993339968&hash=item1b361d4974%3Ag%3AUOAAAeSwbgdpEgO6&amdata=enc%3AAQAKAAAA8PeG5RIuIyokJHJy903%2F5UbxH%2BkDfrlT50PJ7VA%2FXM4N1COW2PO62%2FI7U4Ram4X9XUwBYCwHiUbJPL3fSkDDAcoo7AG8EW2KFDbLjH7NtmQ0r%2BaS4c55xlp1NxbzAsaGhnB0fnInrZpJH8GNAkirDnKQkMgXg38y1%2FKZ%2FuwOqNrHF8M9Y622mgCAQiSlvshL47zYLVcnenk7lGf88GLdc%2BRIUTedX9XwFDRu32yACi4y62UQ6iNFI72hVco4aUiwIB9c%2BYkskQbvVyp1iRl7M9%2B6pZvO9MUtAiAIL3oKdHkfC5fXVf%2Bojyew3KxxZseAmg%3D%3D&mkcid=1&mkrid=711-53200-19255-0&mkevt=1&campid=5339121799&customid=smart_light_strip&toolid=10001",
      "seller_feedback": 31426,
      "top_rated": false,
      "score": 9.0,
      "tags": [
        "smart light strip"
      ],
      "caption": "Transform your home with our Smart RGB Outdoor Lights! \ud83c\udf08 Waterproof and stylish\u2014perfect for any occasion. Grab yours now for just $76.49!\u2728",
      "headline": "\ud83d\udd25\u2728 Smart Permanent Outdoor Lights RGB Waterproof Eaves Lighting for House Decor",
      "blurb": "USD 76.49 steal. Limited stock\u2014grab it now!",
      "emojis": "\ud83d\udd25\u2728"
    },
    {
      "source": "ebay",
      "provider": "ebay",
      "keyword": "smart light strip",
      "title": "100Ft LED Strip Lights, Smart Light with App Remote Control, RGB LED Lights for ",
      "price": 14.89,
      "currency": "USD",
      "image_url": "https://i.ebayimg.com/images/g/KuUAAOSwoXdmKC4-/s-l225.jpg",
      "url": "https://www.ebay.com/itm/266782459674?_skw=smart+light+strip&hash=item3e1d79471a%3Ag%3AKuUAAOSwoXdmKC4-&amdata=enc%3AAQAKAAAA8PeG5RIuIyokJHJy903%2F5UZqOE8xMOfSf8n1qsjMl85rqejuJFexeKdJ66PrQdGaBUO35B73Teu7uQIT%2FbN1wVlR75i0aPOL6WUnApR3layvXYs1mIxffVkpzoGn5lwxKd2ekNxZWiZiUzpGMy56oxeDxe1LppQs45xv3OIwp0o8t3%2F3%2F1up5MOxcnL7Hat2aK0zttj%2Bl8nG1S5%2FJqjmWseHvnxCl1IsLJiXY6r8vjdkRW%2Fqvn18N19XbtDDUTOWg37gzt3ZBTRx8XPDrbZzjP59zWsAPnZl%2BJ6ZzFQYsrNBJXSJX7yirfhJR39Xmv4v1Q%3D%3D&mkcid=1&mkrid=711-53200-19255-0&mkevt=1&campid=5339121799&customid=smart_light_strip&toolid=10001",
      "seller_feedback": 8936,
      "top_rated": false,
      "score": 7.0,
      "tags": [
        "smart light strip"
      ],
      "caption": "100Ft LED Strip Lights, Smart Light with App Remote Control, RGB LED Lights for  \u2022 USD 14.89",
      "headline": "\ud83d\udd25\u2728 100Ft LED Strip Lights, Smart Light with App Remote Control, RGB LED Lights for",
      "blurb": "USD 14.89 steal. Limited stock\u2014grab it now!",
      "emojis": "\ud83d\udd25\u2728"
    },
    {
      "source": "ebay",
      "provider": "ebay",
      "keyword": "smart light strip",
      "title": "eufy Permanent Outdoor Light E22 100ft Smart Light Strip App Control IP67|Refurb",
      "price": 189.99,
      "currency": "USD",
      "image_url": "https://i.ebayimg.com/images/g/5Y8AAOSw6oBnrBYm/s-l225.jpg",
      "url": "https://www.ebay.com/itm/384708438760?_skw=smart+light+strip&hash=item599268eae8%3Ag%3A5Y8AAOSw6oBnrBYm&amdata=enc%3AAQAKAAAA8PeG5RIuIyokJHJy903%2F5UY8yA9rW4Ql%2BJ7xrC%2BJ0biHokSpkevaKXP4LYB9SHYUGVDWXWVh4xYOftqCLIfJ899EUREVpXwDPqPyKzpGOK38oYPByyvtXKjSRZpoBK6HAzx%2BHfkLNIcgFbxef3lV8HLkf0NVW3VC%2FTxbSle9ADqWnKgydncqAV0M%2FynAeIKvUYlYI5w09J64Vxy9GgjOzh2WjMOMVPHaQPz8x1V3HEKmN2PmDMDc6nEN23v52Xg2RjNVVKZb60OKHYtpaZoCNzfGru9sg%2BCsjt68R6o3rIWoYNUdnfRmRqWmaKpYkpltRw%3D%3D&mkcid=1&mkrid=711-53200-19255-0&mkevt=1&campid=5339121799&customid=smart_light_strip&toolid=10001",
      "seller_feedback": 67927,
      "top_rated": false,
      "score": 6.0,
      "tags": [
        "smart light strip"
      ],
      "caption": "eufy Permanent Outdoor Light E22 100ft Smart Light Strip App Control IP67|Refurb \u2022 USD 189.99",
      "headline": "\ud83d\udd25\u2728 eufy Permanent Outdoor Light E22 100ft Smart Light Strip App Control IP67|Refurb",
      "blurb": "USD 189.99 steal. Limited stock\u2014grab it now!",
      "emojis": "\ud83d\udd25\u2728"
    },
    {
      "source": "ebay",
      "provider": "ebay",
      "keyword": "smart light strip",
      "title": "200 Ft LED Strip Lights, Smart Light with App Remote Control, RGB LED 2ROLL100ft",
      "price": 20.89,
      "currency": "USD",
      "image_url": "https://i.ebayimg.com/images/g/~FsAAOSw~W5oXN1B/s-l225.jpg",
      "url": "https://www.ebay.com/itm/376365776719?_skw=smart+light+strip&hash=item57a125ff4f%3Ag%3A~FsAAOSw~W5oXN1B&mkcid=1&mkrid=711-53200-19255-0&mkevt=1&campid=5339121799&customid=smart_light_strip&toolid=10001",
      "seller_feedback": 266,
      "top_rated": false,
      "score": 4.266,
      "tags": [
        "smart light strip"
      ],
      "caption": "200 Ft LED Strip Lights, Smart Light with App Remote Control, RGB LED 2ROLL100ft \u2022 USD 20.89",
      "headline": "\u2728 Illuminate Your Space with Smart LED Strip Lights!",
      "blurb": "Transform your home with 200 ft of vibrant RGB LED strip lights at just $20.89! Hurry, stock is limited\u2014grab your remote-controlled magic now!",
      "emojis": "['\ud83c\udfe0', '\ud83c\udfae']"
    },
    {
      "source": "ebay",
      "provider": "ebay",
      "keyword": "smart light strip",
      "title": "LED Strip Lights, Smart Light with App Remote Control, RGB LED Lights for room",
      "price": 13.21,
      "currency": "USD",
      "image_url": "https://i.ebayimg.com/images/g/SNwAAOSwgERoHAvw/s-l225.jpg",
      "url": "https://www.ebay.com/itm/376279396326?_skw=smart+light+strip&var=644967368879&hash=item579bffefe6%3Ag%3ASNwAAOSwgERoHAvw&amdata=enc%3AAQAKAAAA8PeG5RIuIyokJHJy903%2F5UYyLAxt7HIqhpMjADdXqU1j1oy2xPWGj3JjLT7cmB9TpiVzXRsI3lnMaTj0K1zIz8bbftGPQV4ZOuYi2R%2BXpnkiHa9lYd6wtJomnHZoAG7cJUk1bcYharpJwlJf3wMUE2PMSTiga56LBHTuDaL5g%2BAJRwSFegSeKBq%2BPZPK39HGVAwcdOigwaQGGAn%2BF224oG%2FFjdM9qELNmfjTmnCbBTG307WUlMDvw5Wc8WD4qv1lSp7cBQd9WG566q1SL%2BtzJKzVKIH0TFA41TBOiwWk5PBbfWIrlSncHJuG97dYo8seKg%3D%3D&mkcid=1&mkrid=711-53200-19255-0&mkevt=1&campid=5339121799&customid=smart_light_strip&toolid=10001",
      "seller_feedback": 266,
      "top_rated": false,
      "score": 2.266,
      "tags": [
        "smart light strip"
      ],
      "caption": "Transform your space with vibrant RGB LED Strip Lights! \ud83c\udf08 Control with your phone & set the vibe. Get yours now for just $13.21! \u2728",
      "headline": "\ud83d\udd25\u2728 LED Strip Lights, Smart Light with App Remote Control, RGB LED Lights for room",
      "blurb": "USD 13.21 steal. Limited stock\u2014grab it now!",
      "emojis": "\ud83d\udd25\u2728"
    }
  ]
}